{
    "@id": "dr:cmip6/bddtdic-yr-oc-tavg-l-hxy",
    "@type": "dr-variable-cmip6",
    "almost-unique-identifier": "bddtdic-Oyr",
    "mip_table": [
        "Oyr"
    ],
    "table_entry": "bddtdic",
    "out_name": "bddtdic",
    "questions_and_notes": "",
    "specific_issues": [],
    "contributing_institutions": 6,
    "contributing_models": 8,
    "frequency": "yr",
    "region": "global",
    "modeling_realm": [
        "ocnBgchem"
    ],
    "dimensions": "longitude latitude olevel time",
    "cell_methods": "area: mean where sea time: mean",
    "long_name": "Rate of Change of Dissolved Inorganic Carbon Due to Biological Activity",
    "comment": "Net total of biological terms in time rate of change of dissolved inorganic carbon"
}