{
    "@id": "dr:cmip6/phydiaz-mon-oc-tavg-l-hxy",
    "@type": "dr-variable-cmip6",
    "almost-unique-identifier": "phydiaz-Omon",
    "mip_table": [
        "Omon"
    ],
    "table_entry": "phydiaz",
    "out_name": "phydiaz",
    "questions_and_notes": "",
    "specific_issues": [],
    "contributing_institutions": 7,
    "contributing_models": 10,
    "frequency": "mon",
    "region": "global",
    "modeling_realm": [
        "ocnBgchem"
    ],
    "dimensions": "longitude latitude olevel time",
    "cell_methods": "area: mean where sea time: mean",
    "long_name": "Mole Concentration of Diazotrophs Expressed as Carbon in Sea Water",
    "comment": "carbon concentration from the diazotrophic phytoplankton component alone"
}