{
    "@id": "dr:cmip6/sidmassth-mon-si-tavg-z0f??-hxy",
    "@type": "dr-variable-cmip6",
    "almost-unique-identifier": "sidmassth-SImon",
    "mip_table": [
        "SImon"
    ],
    "table_entry": "sidmassth",
    "out_name": "sidmassth",
    "questions_and_notes": "In cell_methods replace \"where sea\" with  \"where sea_ice\" because this is used for sea-ice budgets.",
    "specific_issues": [],
    "contributing_institutions": 17,
    "contributing_models": 35,
    "frequency": "mon",
    "region": "global",
    "modeling_realm": [
        "seaIce"
    ],
    "dimensions": "longitude latitude time",
    "cell_methods": "area: mean where sea time: mean",
    "long_name": "Sea-Ice Mass Change from Thermodynamics",
    "comment": "Total change in sea-ice mass from thermodynamic processes divided by grid-cell area"
}