{
    "@id": "dr:cmip6/vegfrac-yr-unknown-tavg-z0c-hxy",
    "@type": "dr-variable-cmip6",
    "almost-unique-identifier": "vegFrac-Eyr",
    "mip_table": [
        "Eyr"
    ],
    "table_entry": "vegFrac",
    "out_name": "vegFrac",
    "questions_and_notes": "Is this CF conventions area_type: \"vegetation\"?  Consider eliminating scalar dimension.  For consistency with cnc-Eday, this should have a standard_name of vegetation_area_fraction.",
    "specific_issues": [
        "5:Standard name issue."
    ],
    "contributing_institutions": 10,
    "contributing_models": 15,
    "frequency": "yr",
    "region": "global",
    "modeling_realm": [
        "land"
    ],
    "dimensions": "longitude latitude time typeveg",
    "cell_methods": "area: time: mean",
    "long_name": "Total Vegetated Percentage Cover",
    "comment": "Percentage of grid cell that is covered by vegetation.This SHOULD be the sum of tree, grass (natural and pasture), crop and shrub fractions."
}