{
    "@id": "dr:variables/hurs-subhr-unknown-tpt-h02-hxys",
    "@type": "dr-variable",
    "standard_name": "relative_humidity",
    "variable_root_name": "hurs",
    "units": "%",
    "type": "real",
    "positive": 0.0,
    "sn_status": "approved",
    "branding": {
        "temporalLabelDD": "tpt",
        "verticalLabelDD": "h02",
        "horizontalLabelDD": "hxys",
        "areaLabelDD": "x"
    },
    "definition_qualifier": "none",
    "brand_description": "relative humidity: synoptic samples at a height of (or near) 2 m reported at assorted individual sites",
    "bn_status": "accepted",
    "dimensions": [
        "site",
        "time1",
        "height2m"
    ],
    "cell_methods": "area: point time: point",
    "cell_measures": 0.0,
    "samplingIntervals": [
        "subhr"
    ],
    "regions": [
        "global"
    ],
    "used_in": {
        "cmip6": {
            "@id": "dr:cmip6/hurs-subhr-unknown-tpt-h02-hxys"
        }
    }
}